slug_party/__init__.py
slug_party-0.0.1.dist-info/LICENSE
slug_party-0.0.1.dist-info/METADATA
slug_party-0.0.1.dist-info/WHEEL
slug_party-0.0.1.dist-info/top_level.txt
slug_party-0.0.1.dist-info/RECORD
